nonebot_plugin_rename/__init__.py
nonebot_plugin_rename/card/__init__.py
nonebot_plugin_rename/card/exam_time.py
nonebot_plugin_rename/card/get_times.py
nonebot_plugin_rename/card/hot_search.py
nonebot_plugin_rename/card/message.py
nonebot_plugin_rename/card/mhy_time.py
nonebot_plugin_rename/card/one_word.py
nonebot_plugin_rename/card/status.py
nonebot_plugin_rename/card/year_time.py
nonebot_plugin_rename/config.py
nonebot_plugin_rename/fonts/draw.ttf
nonebot_plugin_rename/main.py
nonebot_plugin_rename/utils/__init__.py
nonebot_plugin_rename/utils/card_choice.py
nonebot_plugin_rename/utils/card_name.py
nonebot_plugin_rename/utils/draw.py
nonebot_plugin_rename/utils/my_yaml.py
nonebot_plugin_rename-1.7.1.dist-info/LICENSE
nonebot_plugin_rename-1.7.1.dist-info/METADATA
nonebot_plugin_rename-1.7.1.dist-info/WHEEL
nonebot_plugin_rename-1.7.1.dist-info/RECORD
