Metadata-Version: 2.1
Name: nonebot-plugin-rename
Version: 1.7.1
Summary: 更改qq机器人的群名片，内置多种有趣名片
License: GPL-3.0
Author: forchannot
Author-email: yy320206@gmail.com
Requires-Python: >=3.8,<4.0
Classifier: License :: OSI Approved :: GNU General Public License v3 (GPLv3)
Classifier: Programming Language :: Python :: 3
Classifier: Programming Language :: Python :: 3.8
Classifier: Programming Language :: Python :: 3.9
Classifier: Programming Language :: Python :: 3.10
Classifier: Programming Language :: Python :: 3.11
Classifier: Programming Language :: Python :: 3.12
Requires-Dist: httpx (>=0.20.0,<1.0.0)
Requires-Dist: nonebot-adapter-onebot (>=2.2.2,<3.0.0)
Requires-Dist: nonebot-plugin-apscheduler (>=0.2.0,<0.3.0)
Requires-Dist: nonebot2 (>=2.0.0,<3.0.0)
Requires-Dist: pillow (>=9.5.0,<10.0.0)
Requires-Dist: psutil (>=5.9.5,<6.0.0)
Requires-Dist: pyyaml (>=6.0,<7.0)
